<?xml version="1.0" encoding="UTF-8"?>
<!DOCTYPE raptornuke-portlet-app PUBLIC "-//Raptornuke//DTD Portlet Application 2.0.0//EN" "http://www.raptornuke.ffcs.cn/dtd/raptornuke-portlet-app_2_0_0.dtd">
<raptornuke-portlet-app>
	<!-- 主数据人员规范性 -->
	<portlet>
		<portlet-name>bpmMainStaff</portlet-name>
		<maximize-edit>true</maximize-edit>
		<instanceable>true</instanceable>
		<standalone-width>800</standalone-width>
		<standalone-height>600</standalone-height>
		<standalone-draggable>true</standalone-draggable>
		<standalone-resizable>true</standalone-resizable>
		<standalone-scrolling>auto</standalone-scrolling>
		<standalone-modal>false</standalone-modal>
		<standalone-auto-height>false</standalone-auto-height>
		<standalone-interval-time>200</standalone-interval-time>
		<header-portlet-javascript>/zkau/web/js/zk.wpd</header-portlet-javascript>
	</portlet>	
	<!-- 人力智慧运营-HR目录与主数据一致性 -->
	<portlet>
		<portlet-name>bpmHr</portlet-name>
		<maximize-edit>true</maximize-edit>
		<instanceable>true</instanceable>
		<standalone-width>800</standalone-width>
		<standalone-height>600</standalone-height>
		<standalone-draggable>true</standalone-draggable>
		<standalone-resizable>true</standalone-resizable>
		<standalone-scrolling>auto</standalone-scrolling>
		<standalone-modal>false</standalone-modal>
		<standalone-auto-height>false</standalone-auto-height>
		<standalone-interval-time>200</standalone-interval-time>
		<header-portlet-javascript>/zkau/web/js/zk.wpd</header-portlet-javascript>
	</portlet>
	<!-- 主数据与渠道一致性 -->
	<portlet>
		<portlet-name>bpmModify</portlet-name>
		<maximize-edit>true</maximize-edit>
		<instanceable>true</instanceable>
		<standalone-width>800</standalone-width>
		<standalone-height>600</standalone-height>
		<standalone-draggable>true</standalone-draggable>
		<standalone-resizable>true</standalone-resizable>
		<standalone-scrolling>auto</standalone-scrolling>
		<standalone-modal>false</standalone-modal>
		<standalone-auto-height>false</standalone-auto-height>
		<standalone-interval-time>200</standalone-interval-time>
		<header-portlet-javascript>/zkau/web/js/zk.wpd</header-portlet-javascript>
	</portlet>


	<portlet>
		<portlet-name>systemConfigPortlet</portlet-name>
		<maximize-edit>true</maximize-edit>
		<instanceable>true</instanceable>
		<standalone-width>800</standalone-width>
		<standalone-height>600</standalone-height>
		<standalone-draggable>true</standalone-draggable>
		<standalone-resizable>true</standalone-resizable>
		<standalone-scrolling>auto</standalone-scrolling>
		<standalone-modal>false</standalone-modal>
		<standalone-auto-height>false</standalone-auto-height>
		<standalone-interval-time>200</standalone-interval-time>
		<header-portlet-javascript>/zkau/web/js/zk.wpd</header-portlet-javascript>
	</portlet>

	
	<portlet>
		<portlet-name>systemConfig</portlet-name>
		<maximize-edit>true</maximize-edit>
		<instanceable>true</instanceable>
		<standalone-width>800</standalone-width>
		<standalone-height>600</standalone-height>
		<standalone-draggable>true</standalone-draggable>
		<standalone-resizable>true</standalone-resizable>
		<standalone-scrolling>auto</standalone-scrolling>
		<standalone-modal>false</standalone-modal>
		<standalone-auto-height>false</standalone-auto-height>
		<standalone-interval-time>200</standalone-interval-time>
		<header-portlet-javascript>/zkau/web/js/zk.wpd</header-portlet-javascript>
	</portlet>
	<portlet>
		<portlet-name>staff</portlet-name>
		<maximize-edit>true</maximize-edit>
		<instanceable>true</instanceable>
		<standalone-width>800</standalone-width>
		<standalone-height>600</standalone-height>
		<standalone-draggable>true</standalone-draggable>
		<standalone-resizable>true</standalone-resizable>
		<standalone-scrolling>auto</standalone-scrolling>
		<standalone-modal>false</standalone-modal>
		<standalone-auto-height>false</standalone-auto-height>
		<standalone-interval-time>200</standalone-interval-time>
		<header-portlet-javascript>/zkau/web/js/zk.wpd</header-portlet-javascript>
	</portlet>
	<portlet>
		<portlet-name>staffPasswordQuery</portlet-name>
		<maximize-edit>true</maximize-edit>
		<instanceable>true</instanceable>
		<standalone-width>800</standalone-width>
		<standalone-height>600</standalone-height>
		<standalone-draggable>true</standalone-draggable>
		<standalone-resizable>true</standalone-resizable>
		<standalone-scrolling>auto</standalone-scrolling>
		<standalone-modal>false</standalone-modal>
		<standalone-auto-height>false</standalone-auto-height>
		<standalone-interval-time>200</standalone-interval-time>
		<header-portlet-javascript>/zkau/web/js/zk.wpd</header-portlet-javascript>
	</portlet>
	<portlet>
		<portlet-name>staffPasswordReset</portlet-name>
		<maximize-edit>true</maximize-edit>
		<instanceable>true</instanceable>
		<standalone-width>800</standalone-width>
		<standalone-height>600</standalone-height>
		<standalone-draggable>true</standalone-draggable>
		<standalone-resizable>true</standalone-resizable>
		<standalone-scrolling>auto</standalone-scrolling>
		<standalone-modal>false</standalone-modal>
		<standalone-auto-height>false</standalone-auto-height>
		<standalone-interval-time>200</standalone-interval-time>
		<header-portlet-javascript>/zkau/web/js/zk.wpd</header-portlet-javascript>
	</portlet>
	<portlet>
		<portlet-name>staffUnlock</portlet-name>
		<maximize-edit>true</maximize-edit>
		<instanceable>true</instanceable>
		<standalone-width>800</standalone-width>
		<standalone-height>600</standalone-height>
		<standalone-draggable>true</standalone-draggable>
		<standalone-resizable>true</standalone-resizable>
		<standalone-scrolling>auto</standalone-scrolling>
		<standalone-modal>false</standalone-modal>
		<standalone-auto-height>false</standalone-auto-height>
		<standalone-interval-time>200</standalone-interval-time>
		<header-portlet-javascript>/zkau/web/js/zk.wpd</header-portlet-javascript>
	</portlet>
	<portlet>
		<portlet-name>staffCustms</portlet-name>
		<maximize-edit>true</maximize-edit>
		<instanceable>true</instanceable>
		<standalone-width>800</standalone-width>
		<standalone-height>600</standalone-height>
		<standalone-draggable>true</standalone-draggable>
		<standalone-resizable>true</standalone-resizable>
		<standalone-scrolling>auto</standalone-scrolling>
		<standalone-modal>false</standalone-modal>
		<standalone-auto-height>false</standalone-auto-height>
		<standalone-interval-time>200</standalone-interval-time>
		<header-portlet-javascript>/zkau/web/js/zk.wpd</header-portlet-javascript>
	</portlet>

	<portlet>
		<portlet-name>party</portlet-name>
		<maximize-edit>true</maximize-edit>
		<instanceable>true</instanceable>
		<standalone-width>800</standalone-width>
		<standalone-height>600</standalone-height>
		<standalone-draggable>true</standalone-draggable>
		<standalone-resizable>true</standalone-resizable>
		<standalone-scrolling>auto</standalone-scrolling>
		<standalone-modal>false</standalone-modal>
		<standalone-auto-height>false</standalone-auto-height>
		<standalone-interval-time>200</standalone-interval-time>
		<header-portlet-javascript>/zkau/web/js/zk.wpd</header-portlet-javascript>
	</portlet>
	<portlet>
		<portlet-name>idNoQuery</portlet-name>
		<maximize-edit>true</maximize-edit>
		<instanceable>true</instanceable>
		<standalone-width>800</standalone-width>
		<standalone-height>600</standalone-height>
		<standalone-draggable>true</standalone-draggable>
		<standalone-resizable>true</standalone-resizable>
		<standalone-scrolling>auto</standalone-scrolling>
		<standalone-modal>false</standalone-modal>
		<standalone-auto-height>false</standalone-auto-height>
		<standalone-interval-time>200</standalone-interval-time>
		<header-portlet-javascript>/zkau/web/js/zk.wpd</header-portlet-javascript>
	</portlet>
	<portlet>
		<portlet-name>organizationTree</portlet-name>
		<maximize-edit>true</maximize-edit>
		<instanceable>true</instanceable>
		<standalone-width>800</standalone-width>
		<standalone-height>600</standalone-height>
		<standalone-draggable>true</standalone-draggable>
		<standalone-resizable>true</standalone-resizable>
		<standalone-scrolling>auto</standalone-scrolling>
		<standalone-modal>false</standalone-modal>
		<standalone-auto-height>false</standalone-auto-height>
		<standalone-interval-time>200</standalone-interval-time>
		<header-portlet-javascript>/zkau/web/js/zk.wpd</header-portlet-javascript>
	</portlet>
	<portlet>
		<portlet-name>agentTree</portlet-name>
		<maximize-edit>true</maximize-edit>
		<instanceable>true</instanceable>
		<standalone-width>800</standalone-width>
		<standalone-height>600</standalone-height>
		<standalone-draggable>true</standalone-draggable>
		<standalone-resizable>true</standalone-resizable>
		<standalone-scrolling>auto</standalone-scrolling>
		<standalone-modal>false</standalone-modal>
		<standalone-auto-height>false</standalone-auto-height>
		<standalone-interval-time>200</standalone-interval-time>
		<header-portlet-javascript>/zkau/web/js/zk.wpd</header-portlet-javascript>
	</portlet>
	<portlet>
		<portlet-name>custms</portlet-name>
		<maximize-edit>true</maximize-edit>
		<instanceable>true</instanceable>
		<standalone-width>800</standalone-width>
		<standalone-height>600</standalone-height>
		<standalone-draggable>true</standalone-draggable>
		<standalone-resizable>true</standalone-resizable>
		<standalone-scrolling>auto</standalone-scrolling>
		<standalone-modal>false</standalone-modal>
		<standalone-auto-height>false</standalone-auto-height>
		<standalone-interval-time>200</standalone-interval-time>
		<header-portlet-javascript>/zkau/web/js/zk.wpd</header-portlet-javascript>
	</portlet>
	<portlet>
		<portlet-name>custunit</portlet-name>
		<maximize-edit>true</maximize-edit>
		<instanceable>true</instanceable>
		<standalone-width>800</standalone-width>
		<standalone-height>600</standalone-height>
		<standalone-draggable>true</standalone-draggable>
		<standalone-resizable>true</standalone-resizable>
		<standalone-scrolling>auto</standalone-scrolling>
		<standalone-modal>false</standalone-modal>
		<standalone-auto-height>false</standalone-auto-height>
		<standalone-interval-time>200</standalone-interval-time>
		<header-portlet-javascript>/zkau/web/js/zk.wpd</header-portlet-javascript>
	</portlet>
	<portlet>
		<portlet-name>organizationManager</portlet-name>
		<maximize-edit>true</maximize-edit>
		<instanceable>true</instanceable>
		<standalone-width>1000</standalone-width>
		<standalone-height>800</standalone-height>
		<standalone-draggable>true</standalone-draggable>
		<standalone-resizable>true</standalone-resizable>
		<standalone-scrolling>auto</standalone-scrolling>
		<standalone-modal>false</standalone-modal>
		<standalone-auto-height>false</standalone-auto-height>
		<standalone-interval-time>200</standalone-interval-time>
		<header-portlet-javascript>/zkau/web/js/zk.wpd</header-portlet-javascript>
	</portlet>
	<!-- 岗位 -->
	<portlet>
		<portlet-name>position</portlet-name>
		<maximize-edit>true</maximize-edit>
		<instanceable>true</instanceable>
		<standalone-width>800</standalone-width>
		<standalone-height>600</standalone-height>
		<standalone-draggable>true</standalone-draggable>
		<standalone-resizable>true</standalone-resizable>
		<standalone-scrolling>auto</standalone-scrolling>
		<standalone-modal>false</standalone-modal>
		<standalone-auto-height>false</standalone-auto-height>
		<standalone-interval-time>200</standalone-interval-time>
		<header-portlet-javascript>/zkau/web/js/zk.wpd</header-portlet-javascript>
	</portlet>
	<!-- 审核 -->
	<portlet>
		<portlet-name>operateLog</portlet-name>
		<maximize-edit>true</maximize-edit>
		<instanceable>true</instanceable>
		<standalone-width>800</standalone-width>
		<standalone-height>600</standalone-height>
		<standalone-draggable>true</standalone-draggable>
		<standalone-resizable>true</standalone-resizable>
		<standalone-scrolling>auto</standalone-scrolling>
		<standalone-modal>false</standalone-modal>
		<standalone-auto-height>false</standalone-auto-height>
		<standalone-interval-time>200</standalone-interval-time>
		<header-portlet-javascript>/zkau/web/js/zk.wpd</header-portlet-javascript>
	</portlet>
	<!-- 激活 -->
	<portlet>
		<portlet-name>activation</portlet-name>
		<maximize-edit>true</maximize-edit>
		<instanceable>true</instanceable>
		<standalone-width>800</standalone-width>
		<standalone-height>600</standalone-height>
		<standalone-draggable>true</standalone-draggable>
		<standalone-resizable>true</standalone-resizable>
		<standalone-scrolling>auto</standalone-scrolling>
		<standalone-modal>false</standalone-modal>
		<standalone-auto-height>false</standalone-auto-height>
		<standalone-interval-time>200</standalone-interval-time>
		<header-portlet-javascript>/zkau/web/js/zk.wpd</header-portlet-javascript>
	</portlet>
	<portlet>
		<portlet-name>zkdemo</portlet-name>
		<maximize-edit>true</maximize-edit>
		<instanceable>true</instanceable>
		<standalone-width>800</standalone-width>
		<standalone-height>600</standalone-height>
		<standalone-draggable>true</standalone-draggable>
		<standalone-resizable>true</standalone-resizable>
		<standalone-scrolling>auto</standalone-scrolling>
		<standalone-modal>false</standalone-modal>
		<standalone-auto-height>false</standalone-auto-height>
		<standalone-interval-time>200</standalone-interval-time>
		<header-portlet-javascript>/zkau/web/js/zk.wpd</header-portlet-javascript>
	</portlet>
	<portlet>
		<portlet-name>informationManagerPortlet</portlet-name>
		<!--icon>/ApplicationImage/informationManager.png</icon -->
		<maximize-edit>true</maximize-edit>
		<instanceable>true</instanceable>
		<standalone-modal>false</standalone-modal>
		<ajaxable>false</ajaxable>
	</portlet>
	<portlet>
		<portlet-name>informationCenterPortlet</portlet-name>
		<!--icon>/ApplicationImage/informationCenter.png</icon -->
		<maximize-edit>true</maximize-edit>
		<instanceable>true</instanceable>
		<standalone-width>1000</standalone-width>
		<standalone-height>600</standalone-height>
		<standalone-modal>false</standalone-modal>
		<ajaxable>false</ajaxable>
	</portlet>
	<portlet>
		<portlet-name>bulletinNewsPortlet</portlet-name>
		<!--icon>/ApplicationImage/bulletinNews.png</icon -->
		<maximize-edit>true</maximize-edit>
		<instanceable>true</instanceable>
		<standalone-modal>false</standalone-modal>
		<ajaxable>false</ajaxable>
	</portlet>
	<portlet>
		<portlet-name>bulletinBulletinPortlet</portlet-name>
		<!--icon>/ApplicationImage/bulletinBulletin.png</icon -->
		<maximize-edit>true</maximize-edit>
		<instanceable>true</instanceable>
		<standalone-modal>false</standalone-modal>
		<ajaxable>false</ajaxable>
	</portlet>
	<portlet>
		<portlet-name>bulletinImagePortlet</portlet-name>
		<!--icon>/ApplicationImage/bulletinImage.png</icon -->
		<maximize-edit>true</maximize-edit>
		<instanceable>true</instanceable>
		<standalone-modal>false</standalone-modal>
		<ajaxable>false</ajaxable>
	</portlet>
	<portlet>
		<portlet-name>dataPermissionManager</portlet-name>
		<control-panel-entry-category>portal</control-panel-entry-category>
		<control-panel-entry-weight>10.0</control-panel-entry-weight>
		<header-portlet-javascript>/zkau/web/js/zk.wpd</header-portlet-javascript>
	</portlet>
	<portlet>
		<portlet-name>compare</portlet-name>
		<maximize-edit>true</maximize-edit>
		<instanceable>true</instanceable>
		<standalone-width>800</standalone-width>
		<standalone-height>600</standalone-height>
		<standalone-draggable>true</standalone-draggable>
		<standalone-resizable>true</standalone-resizable>
		<standalone-scrolling>auto</standalone-scrolling>
		<standalone-modal>false</standalone-modal>
		<standalone-auto-height>false</standalone-auto-height>
		<standalone-interval-time>200</standalone-interval-time>
		<header-portlet-javascript>/zkau/web/js/zk.wpd</header-portlet-javascript>
	</portlet>
	<!-- 系统接口配置 -->
	<portlet>
		<portlet-name>interfaceConfig</portlet-name>
		<maximize-edit>true</maximize-edit>
		<instanceable>true</instanceable>
		<standalone-width>800</standalone-width>
		<standalone-height>600</standalone-height>
		<standalone-draggable>true</standalone-draggable>
		<standalone-resizable>true</standalone-resizable>
		<standalone-scrolling>auto</standalone-scrolling>
		<standalone-modal>false</standalone-modal>
		<standalone-auto-height>false</standalone-auto-height>
		<standalone-interval-time>200</standalone-interval-time>
		<header-portlet-javascript>/zkau/web/js/zk.wpd</header-portlet-javascript>
	</portlet>
	<!-- 系统接口短信通知配置 -->
	<portlet>
		<portlet-name>messageConfig</portlet-name>
		<maximize-edit>true</maximize-edit>
		<instanceable>true</instanceable>
		<standalone-width>800</standalone-width>
		<standalone-height>600</standalone-height>
		<standalone-draggable>true</standalone-draggable>
		<standalone-resizable>true</standalone-resizable>
		<standalone-scrolling>auto</standalone-scrolling>
		<standalone-modal>false</standalone-modal>
		<standalone-auto-height>false</standalone-auto-height>
		<standalone-interval-time>200</standalone-interval-time>
		<header-portlet-javascript>/zkau/web/js/zk.wpd</header-portlet-javascript>
	</portlet>
	<!-- 员工角色 -->
	<portlet>
		<portlet-name>staffRole</portlet-name>
		<maximize-edit>true</maximize-edit>
		<instanceable>true</instanceable>
		<standalone-width>800</standalone-width>
		<standalone-height>600</standalone-height>
		<standalone-draggable>true</standalone-draggable>
		<standalone-resizable>true</standalone-resizable>
		<standalone-scrolling>auto</standalone-scrolling>
		<standalone-modal>false</standalone-modal>
		<standalone-auto-height>false</standalone-auto-height>
		<standalone-interval-time>200</standalone-interval-time>
		<header-portlet-javascript>/zkau/web/js/zk.wpd</header-portlet-javascript>
	</portlet>
	<!-- 员工系统 -->
	<portlet>
		<portlet-name>staffSys</portlet-name>
		<maximize-edit>true</maximize-edit>
		<instanceable>true</instanceable>
		<standalone-width>800</standalone-width>
		<standalone-height>600</standalone-height>
		<standalone-draggable>true</standalone-draggable>
		<standalone-resizable>true</standalone-resizable>
		<standalone-scrolling>auto</standalone-scrolling>
		<standalone-modal>false</standalone-modal>
		<standalone-auto-height>false</standalone-auto-height>
		<standalone-interval-time>200</standalone-interval-time>
		<header-portlet-javascript>/zkau/web/js/zk.wpd</header-portlet-javascript>
	</portlet>
	<!-- 角色权限 -->
	<portlet>
		<portlet-name>roleAuth</portlet-name>
		<maximize-edit>true</maximize-edit>
		<instanceable>true</instanceable>
		<standalone-width>800</standalone-width>
		<standalone-height>600</standalone-height>
		<standalone-draggable>true</standalone-draggable>
		<standalone-resizable>true</standalone-resizable>
		<standalone-scrolling>auto</standalone-scrolling>
		<standalone-modal>false</standalone-modal>
		<standalone-auto-height>false</standalone-auto-height>
		<standalone-interval-time>200</standalone-interval-time>
		<header-portlet-javascript>/zkau/web/js/zk.wpd</header-portlet-javascript>
	</portlet>
	<!-- 访问配置 -->
	<portlet>
		<portlet-name>accConfig</portlet-name>
		<maximize-edit>true</maximize-edit>
		<instanceable>true</instanceable>
		<standalone-width>800</standalone-width>
		<standalone-height>600</standalone-height>
		<standalone-draggable>true</standalone-draggable>
		<standalone-resizable>true</standalone-resizable>
		<standalone-scrolling>auto</standalone-scrolling>
		<standalone-modal>false</standalone-modal>
		<standalone-auto-height>false</standalone-auto-height>
		<standalone-interval-time>200</standalone-interval-time>
		<header-portlet-javascript>/zkau/web/js/zk.wpd</header-portlet-javascript>
	</portlet>
	<!-- 组织结构管理 -->
	<portlet>
		<portlet-name>structure</portlet-name>
		<maximize-edit>true</maximize-edit>
		<instanceable>true</instanceable>
		<standalone-width>800</standalone-width>
		<standalone-height>600</standalone-height>
		<standalone-draggable>true</standalone-draggable>
		<standalone-resizable>true</standalone-resizable>
		<standalone-scrolling>auto</standalone-scrolling>
		<standalone-modal>false</standalone-modal>
		<standalone-auto-height>false</standalone-auto-height>
		<standalone-interval-time>200</standalone-interval-time>
		<header-portlet-javascript>/zkau/web/js/zk.wpd</header-portlet-javascript>
	</portlet>
	<!-- 组织关系稽核 -->
	<portlet>
		<portlet-name>orgRelation</portlet-name>
		<maximize-edit>true</maximize-edit>
		<instanceable>true</instanceable>
		<standalone-width>800</standalone-width>
		<standalone-height>600</standalone-height>
		<standalone-draggable>true</standalone-draggable>
		<standalone-resizable>true</standalone-resizable>
		<standalone-scrolling>auto</standalone-scrolling>
		<standalone-modal>false</standalone-modal>
		<standalone-auto-height>false</standalone-auto-height>
		<standalone-interval-time>200</standalone-interval-time>
		<header-portlet-javascript>/zkau/web/js/zk.wpd</header-portlet-javascript>
	</portlet>
	<!-- 稽核管理 -->
	<portlet>
		<portlet-name>audit</portlet-name>
		<maximize-edit>true</maximize-edit>
		<instanceable>true</instanceable>
		<standalone-width>800</standalone-width>
		<standalone-height>600</standalone-height>
		<standalone-draggable>true</standalone-draggable>
		<standalone-resizable>true</standalone-resizable>
		<standalone-scrolling>auto</standalone-scrolling>
		<standalone-modal>false</standalone-modal>
		<standalone-auto-height>false</standalone-auto-height>
		<standalone-interval-time>200</standalone-interval-time>
		<header-portlet-javascript>/zkau/web/js/zk.wpd</header-portlet-javascript>
	</portlet>
	<!-- 身份证管理 -->
	<portlet>
		<portlet-name>identity</portlet-name>
		<maximize-edit>true</maximize-edit>
		<instanceable>true</instanceable>
		<standalone-width>800</standalone-width>
		<standalone-height>600</standalone-height>
		<standalone-draggable>true</standalone-draggable>
		<standalone-resizable>true</standalone-resizable>
		<standalone-scrolling>auto</standalone-scrolling>
		<standalone-modal>false</standalone-modal>
		<standalone-auto-height>false</standalone-auto-height>
		<standalone-interval-time>200</standalone-interval-time>
		<header-portlet-javascript>/zkau/web/js/zk.wpd</header-portlet-javascript>
	</portlet>
	<!-- 省内账号修正 -->
	<portlet>
		<portlet-name>group</portlet-name>
		<maximize-edit>true</maximize-edit>
		<instanceable>true</instanceable>
		<standalone-width>800</standalone-width>
		<standalone-height>600</standalone-height>
		<standalone-draggable>true</standalone-draggable>
		<standalone-resizable>true</standalone-resizable>
		<standalone-scrolling>auto</standalone-scrolling>
		<standalone-modal>false</standalone-modal>
		<standalone-auto-height>false</standalone-auto-height>
		<standalone-interval-time>200</standalone-interval-time>
		<header-portlet-javascript>/zkau/web/js/zk.wpd</header-portlet-javascript>
	</portlet>
	<!-- 集团GUID关联 -->
	<portlet>
		<portlet-name>groupGuid</portlet-name>
		<maximize-edit>true</maximize-edit>
		<instanceable>true</instanceable>
		<standalone-width>800</standalone-width>
		<standalone-height>600</standalone-height>
		<standalone-draggable>true</standalone-draggable>
		<standalone-resizable>true</standalone-resizable>
		<standalone-scrolling>auto</standalone-scrolling>
		<standalone-modal>false</standalone-modal>
		<standalone-auto-height>false</standalone-auto-height>
		<standalone-interval-time>200</standalone-interval-time>
		<header-portlet-javascript>/zkau/web/js/zk.wpd</header-portlet-javascript>
	</portlet>
	<!-- 集团数据与主数据关系管理 -->
	<portlet>
		<portlet-name>groupUom</portlet-name>
		<maximize-edit>true</maximize-edit>
		<instanceable>true</instanceable>
		<standalone-width>800</standalone-width>
		<standalone-height>600</standalone-height>
		<standalone-draggable>true</standalone-draggable>
		<standalone-resizable>true</standalone-resizable>
		<standalone-scrolling>auto</standalone-scrolling>
		<standalone-modal>false</standalone-modal>
		<standalone-auto-height>false</standalone-auto-height>
		<standalone-interval-time>200</standalone-interval-time>
		<header-portlet-javascript>/zkau/web/js/zk.wpd</header-portlet-javascript>
	</portlet>
	<!-- 营销聚合2015-新营销树 -->
	<portlet>
		<portlet-name>marketingTree</portlet-name>
		<maximize-edit>true</maximize-edit>
		<instanceable>true</instanceable>
		<standalone-width>800</standalone-width>
		<standalone-height>600</standalone-height>
		<standalone-draggable>true</standalone-draggable>
		<standalone-resizable>true</standalone-resizable>
		<standalone-scrolling>auto</standalone-scrolling>
		<standalone-modal>false</standalone-modal>
		<standalone-auto-height>false</standalone-auto-height>
		<standalone-interval-time>200</standalone-interval-time>
		<header-portlet-javascript>/zkau/web/js/zk.wpd</header-portlet-javascript>
	</portlet>
	<!-- 营销聚合2017-新营销树 -->
	<portlet>
		<portlet-name>newSeventeenMarketingTree</portlet-name>
		<maximize-edit>true</maximize-edit>
		<instanceable>true</instanceable>
		<standalone-width>800</standalone-width>
		<standalone-height>600</standalone-height>
		<standalone-draggable>true</standalone-draggable>
		<standalone-resizable>true</standalone-resizable>
		<standalone-scrolling>auto</standalone-scrolling>
		<standalone-modal>false</standalone-modal>
		<standalone-auto-height>false</standalone-auto-height>
		<standalone-interval-time>200</standalone-interval-time>
		<header-portlet-javascript>/zkau/web/js/zk.wpd</header-portlet-javascript>
	</portlet>
	<!-- 营销聚合2016-新营销树 -->
	<portlet>
		<portlet-name>newMarketingTree</portlet-name>
		<maximize-edit>true</maximize-edit>
		<instanceable>true</instanceable>
		<standalone-width>800</standalone-width>
		<standalone-height>600</standalone-height>
		<standalone-draggable>true</standalone-draggable>
		<standalone-resizable>true</standalone-resizable>
		<standalone-scrolling>auto</standalone-scrolling>
		<standalone-modal>false</standalone-modal>
		<standalone-auto-height>false</standalone-auto-height>
		<standalone-interval-time>200</standalone-interval-time>
		<header-portlet-javascript>/zkau/web/js/zk.wpd</header-portlet-javascript>
	</portlet>
	<!-- 营销聚合2015-新营销单元 -->
	<portlet>
		<portlet-name>marketingUnit</portlet-name>
		<maximize-edit>true</maximize-edit>
		<instanceable>true</instanceable>
		<standalone-width>800</standalone-width>
		<standalone-height>600</standalone-height>
		<standalone-draggable>true</standalone-draggable>
		<standalone-resizable>true</standalone-resizable>
		<standalone-scrolling>auto</standalone-scrolling>
		<standalone-modal>false</standalone-modal>
		<standalone-auto-height>false</standalone-auto-height>
		<standalone-interval-time>200</standalone-interval-time>
		<header-portlet-javascript>/zkau/web/js/zk.wpd</header-portlet-javascript>
	</portlet>
	<!-- 营销聚合2016-新营销单元 -->
	<portlet>
		<portlet-name>newMarketingUnit</portlet-name>
		<maximize-edit>true</maximize-edit>
		<instanceable>true</instanceable>
		<standalone-width>800</standalone-width>
		<standalone-height>600</standalone-height>
		<standalone-draggable>true</standalone-draggable>
		<standalone-resizable>true</standalone-resizable>
		<standalone-scrolling>auto</standalone-scrolling>
		<standalone-modal>false</standalone-modal>
		<standalone-auto-height>false</standalone-auto-height>
		<standalone-interval-time>200</standalone-interval-time>
		<header-portlet-javascript>/zkau/web/js/zk.wpd</header-portlet-javascript>
	</portlet>
	<!-- 营销聚合2017-新营销单元 -->
	<portlet>
		<portlet-name>newSeventeenMarketingUnit</portlet-name>
		<maximize-edit>true</maximize-edit>
		<instanceable>true</instanceable>
		<standalone-width>800</standalone-width>
		<standalone-height>600</standalone-height>
		<standalone-draggable>true</standalone-draggable>
		<standalone-resizable>true</standalone-resizable>
		<standalone-scrolling>auto</standalone-scrolling>
		<standalone-modal>false</standalone-modal>
		<standalone-auto-height>false</standalone-auto-height>
		<standalone-interval-time>200</standalone-interval-time>
		<header-portlet-javascript>/zkau/web/js/zk.wpd</header-portlet-javascript>
	</portlet>
	<!-- 营销聚合-员工管理 -->
	<portlet>
		<portlet-name>marketingStaff</portlet-name>
		<maximize-edit>true</maximize-edit>
		<instanceable>true</instanceable>
		<standalone-width>800</standalone-width>
		<standalone-height>600</standalone-height>
		<standalone-draggable>true</standalone-draggable>
		<standalone-resizable>true</standalone-resizable>
		<standalone-scrolling>auto</standalone-scrolling>
		<standalone-modal>false</standalone-modal>
		<standalone-auto-height>false</standalone-auto-height>
		<standalone-interval-time>200</standalone-interval-time>
		<header-portlet-javascript>/zkau/web/js/zk.wpd</header-portlet-javascript>
	</portlet>
	<!-- 数据操作人查询 -->
	<portlet>
		<portlet-name>dataOperatorQuery</portlet-name>
		<maximize-edit>true</maximize-edit>
		<instanceable>true</instanceable>
		<standalone-width>800</standalone-width>
		<standalone-height>600</standalone-height>
		<standalone-draggable>true</standalone-draggable>
		<standalone-resizable>true</standalone-resizable>
		<standalone-scrolling>auto</standalone-scrolling>
		<standalone-modal>false</standalone-modal>
		<standalone-auto-height>false</standalone-auto-height>
		<standalone-interval-time>200</standalone-interval-time>
		<header-portlet-javascript>/zkau/web/js/zk.wpd</header-portlet-javascript>
	</portlet>
	<!-- 下发系统查询 -->
	<portlet>
		<portlet-name>systemIssuedQuery</portlet-name>
		<maximize-edit>true</maximize-edit>
		<instanceable>true</instanceable>
		<standalone-width>800</standalone-width>
		<standalone-height>600</standalone-height>
		<standalone-draggable>true</standalone-draggable>
		<standalone-resizable>true</standalone-resizable>
		<standalone-scrolling>auto</standalone-scrolling>
		<standalone-modal>false</standalone-modal>
		<standalone-auto-height>false</standalone-auto-height>
		<standalone-interval-time>200</standalone-interval-time>
		<header-portlet-javascript>/zkau/web/js/zk.wpd</header-portlet-javascript>
	</portlet>
	<!-- 财务树管理 -->
	<portlet>
		<portlet-name>costTree</portlet-name>
		<maximize-edit>true</maximize-edit>
		<instanceable>true</instanceable>
		<standalone-width>800</standalone-width>
		<standalone-height>600</standalone-height>
		<standalone-draggable>true</standalone-draggable>
		<standalone-resizable>true</standalone-resizable>
		<standalone-scrolling>auto</standalone-scrolling>
		<standalone-modal>false</standalone-modal>
		<standalone-auto-height>false</standalone-auto-height>
		<standalone-interval-time>200</standalone-interval-time>
		<header-portlet-javascript>/zkau/web/js/zk.wpd</header-portlet-javascript>
	</portlet>
	<!-- 财务单元管理 -->
	<portlet>
		<portlet-name>costUnit</portlet-name>
		<maximize-edit>true</maximize-edit>
		<instanceable>true</instanceable>
		<standalone-width>800</standalone-width>
		<standalone-height>600</standalone-height>
		<standalone-draggable>true</standalone-draggable>
		<standalone-resizable>true</standalone-resizable>
		<standalone-scrolling>auto</standalone-scrolling>
		<standalone-modal>false</standalone-modal>
		<standalone-auto-height>false</standalone-auto-height>
		<standalone-interval-time>200</standalone-interval-time>
		<header-portlet-javascript>/zkau/web/js/zk.wpd</header-portlet-javascript>
	</portlet>

	<!-- 财务中心组织查询 -->
	<portlet>
		<portlet-name>financialCenter</portlet-name>
		<maximize-edit>true</maximize-edit>
		<instanceable>true</instanceable>
		<standalone-width>800</standalone-width>
		<standalone-height>600</standalone-height>
		<standalone-draggable>true</standalone-draggable>
		<standalone-resizable>true</standalone-resizable>
		<standalone-scrolling>auto</standalone-scrolling>
		<standalone-modal>false</standalone-modal>
		<standalone-auto-height>false</standalone-auto-height>
		<standalone-interval-time>200</standalone-interval-time>
		<header-portlet-javascript>/zkau/web/js/zk.wpd</header-portlet-javascript>
	</portlet>

	<!-- 下发查询 -->
	<portlet>
		<portlet-name>publishQuery</portlet-name>
		<maximize-edit>true</maximize-edit>
		<instanceable>true</instanceable>
		<standalone-width>800</standalone-width>
		<standalone-height>600</standalone-height>
		<standalone-draggable>true</standalone-draggable>
		<standalone-resizable>true</standalone-resizable>
		<standalone-scrolling>auto</standalone-scrolling>
		<standalone-modal>false</standalone-modal>
		<standalone-auto-height>false</standalone-auto-height>
		<standalone-interval-time>200</standalone-interval-time>
		<header-portlet-javascript>/zkau/web/js/zk.wpd</header-portlet-javascript>
	</portlet>

	<!-- ITSM网点校验 -->
	<portlet>
		<portlet-name>orgNetworkCheck</portlet-name>
		<maximize-edit>true</maximize-edit>
		<instanceable>true</instanceable>
		<standalone-width>800</standalone-width>
		<standalone-height>600</standalone-height>
		<standalone-draggable>true</standalone-draggable>
		<standalone-resizable>true</standalone-resizable>
		<standalone-scrolling>auto</standalone-scrolling>
		<standalone-modal>false</standalone-modal>
		<standalone-auto-height>false</standalone-auto-height>
		<standalone-interval-time>200</standalone-interval-time>
		<header-portlet-javascript>/zkau/web/js/zk.wpd</header-portlet-javascript>
	</portlet>

	<!-- 域内业务关系管理 -->
	<portlet>
		<portlet-name>tran</portlet-name>
		<maximize-edit>true</maximize-edit>
		<instanceable>true</instanceable>
		<standalone-width>800</standalone-width>
		<standalone-height>600</standalone-height>
		<standalone-draggable>true</standalone-draggable>
		<standalone-resizable>true</standalone-resizable>
		<standalone-scrolling>auto</standalone-scrolling>
		<standalone-modal>false</standalone-modal>
		<standalone-auto-height>false</standalone-auto-height>
		<standalone-interval-time>200</standalone-interval-time>
		<header-portlet-javascript>/zkau/web/js/zk.wpd</header-portlet-javascript>
	</portlet>

	<!-- 跨域内外业务关系管理 -->
	<portlet>
		<portlet-name>uomGroupTran</portlet-name>
		<maximize-edit>true</maximize-edit>
		<instanceable>true</instanceable>
		<standalone-width>800</standalone-width>
		<standalone-height>600</standalone-height>
		<standalone-draggable>true</standalone-draggable>
		<standalone-resizable>true</standalone-resizable>
		<standalone-scrolling>auto</standalone-scrolling>
		<standalone-modal>false</standalone-modal>
		<standalone-auto-height>false</standalone-auto-height>
		<standalone-interval-time>200</standalone-interval-time>
		<header-portlet-javascript>/zkau/web/js/zk.wpd</header-portlet-javascript>
	</portlet>
	<!-- 集团mss成本中心展示 -->
	<portlet>
		<portlet-name>mssCostTree</portlet-name>
		<maximize-edit>true</maximize-edit>
		<instanceable>true</instanceable>
		<standalone-width>800</standalone-width>
		<standalone-height>600</standalone-height>
		<standalone-draggable>true</standalone-draggable>
		<standalone-resizable>true</standalone-resizable>
		<standalone-scrolling>auto</standalone-scrolling>
		<standalone-modal>false</standalone-modal>
		<standalone-auto-height>false</standalone-auto-height>
		<standalone-interval-time>200</standalone-interval-time>
		<header-portlet-javascript>/zkau/web/js/zk.wpd</header-portlet-javascript>
	</portlet>
	<!-- 集团mss利润中心展示 -->
	<portlet>
		<portlet-name>mssProfitTree</portlet-name>
		<maximize-edit>true</maximize-edit>
		<instanceable>true</instanceable>
		<standalone-width>800</standalone-width>
		<standalone-height>600</standalone-height>
		<standalone-draggable>true</standalone-draggable>
		<standalone-resizable>true</standalone-resizable>
		<standalone-scrolling>auto</standalone-scrolling>
		<standalone-modal>false</standalone-modal>
		<standalone-auto-height>false</standalone-auto-height>
		<standalone-interval-time>200</standalone-interval-time>
		<header-portlet-javascript>/zkau/web/js/zk.wpd</header-portlet-javascript>
	</portlet>
	<!-- 统一目录树管理 -->
	<portlet>
		<portlet-name>unitedDirectoryTree</portlet-name>
		<maximize-edit>true</maximize-edit>
		<instanceable>true</instanceable>
		<standalone-width>800</standalone-width>
		<standalone-height>600</standalone-height>
		<standalone-draggable>true</standalone-draggable>
		<standalone-resizable>true</standalone-resizable>
		<standalone-scrolling>auto</standalone-scrolling>
		<standalone-modal>false</standalone-modal>
		<standalone-auto-height>false</standalone-auto-height>
		<standalone-interval-time>200</standalone-interval-time>
		<header-portlet-javascript>/zkau/web/js/zk.wpd</header-portlet-javascript>
	</portlet>
	<!-- 集团经营主体管理 -->
	<portlet>
		<portlet-name>grpOperators</portlet-name>
		<maximize-edit>true</maximize-edit>
		<instanceable>true</instanceable>
		<standalone-width>800</standalone-width>
		<standalone-height>600</standalone-height>
		<standalone-draggable>true</standalone-draggable>
		<standalone-resizable>true</standalone-resizable>
		<standalone-scrolling>auto</standalone-scrolling>
		<standalone-modal>false</standalone-modal>
		<standalone-auto-height>false</standalone-auto-height>
		<standalone-interval-time>200</standalone-interval-time>
		<header-portlet-javascript>/zkau/web/js/zk.wpd</header-portlet-javascript>
	</portlet>
	<!-- 集团渠道单元管理 -->
	<portlet>
		<portlet-name>grpChannel</portlet-name>
		<maximize-edit>true</maximize-edit>
		<instanceable>true</instanceable>
		<standalone-width>800</standalone-width>
		<standalone-height>600</standalone-height>
		<standalone-draggable>true</standalone-draggable>
		<standalone-resizable>true</standalone-resizable>
		<standalone-scrolling>auto</standalone-scrolling>
		<standalone-modal>false</standalone-modal>
		<standalone-auto-height>false</standalone-auto-height>
		<standalone-interval-time>200</standalone-interval-time>
		<header-portlet-javascript>/zkau/web/js/zk.wpd</header-portlet-javascript>
	</portlet>
	<!-- 集团销售员管理 -->
	<portlet>
		<portlet-name>grpStaff</portlet-name>
		<maximize-edit>true</maximize-edit>
		<instanceable>true</instanceable>
		<standalone-width>800</standalone-width>
		<standalone-height>600</standalone-height>
		<standalone-draggable>true</standalone-draggable>
		<standalone-resizable>true</standalone-resizable>
		<standalone-scrolling>auto</standalone-scrolling>
		<standalone-modal>false</standalone-modal>
		<standalone-auto-height>false</standalone-auto-height>
		<standalone-interval-time>200</standalone-interval-time>
		<header-portlet-javascript>/zkau/web/js/zk.wpd</header-portlet-javascript>
	</portlet>

	<!-- 全息网格单元树管理 -->
	<portlet>
		<portlet-name>gridUnitTree</portlet-name>
		<maximize-edit>true</maximize-edit>
		<instanceable>true</instanceable>
		<standalone-width>800</standalone-width>
		<standalone-height>600</standalone-height>
		<standalone-draggable>true</standalone-draggable>
		<standalone-resizable>true</standalone-resizable>
		<standalone-scrolling>auto</standalone-scrolling>
		<standalone-modal>false</standalone-modal>
		<standalone-auto-height>false</standalone-auto-height>
		<standalone-interval-time>200</standalone-interval-time>
		<header-portlet-javascript>/zkau/web/js/zk.wpd</header-portlet-javascript>
	</portlet>
	
	<!-- 全息网格2017单元树管理 -->
	<portlet>
		<portlet-name>gridSeventeenUnitTree</portlet-name>
		<maximize-edit>true</maximize-edit>
		<instanceable>true</instanceable>
		<standalone-width>800</standalone-width>
		<standalone-height>600</standalone-height>
		<standalone-draggable>true</standalone-draggable>
		<standalone-resizable>true</standalone-resizable>
		<standalone-scrolling>auto</standalone-scrolling>
		<standalone-modal>false</standalone-modal>
		<standalone-auto-height>false</standalone-auto-height>
		<standalone-interval-time>200</standalone-interval-time>
		<header-portlet-javascript>/zkau/web/js/zk.wpd</header-portlet-javascript>
	</portlet>

	<!-- 全息网格单元管理 -->
	<portlet>
		<portlet-name>gridUnit</portlet-name>
		<maximize-edit>true</maximize-edit>
		<instanceable>true</instanceable>
		<standalone-width>800</standalone-width>
		<standalone-height>600</standalone-height>
		<standalone-draggable>true</standalone-draggable>
		<standalone-resizable>true</standalone-resizable>
		<standalone-scrolling>auto</standalone-scrolling>
		<standalone-modal>false</standalone-modal>
		<standalone-auto-height>false</standalone-auto-height>
		<standalone-interval-time>200</standalone-interval-time>
		<header-portlet-javascript>/zkau/web/js/zk.wpd</header-portlet-javascript>
	</portlet>

	<!-- 员工网格单元关系管理 -->
	<portlet>
		<portlet-name>staffGridUnitTran</portlet-name>
		<maximize-edit>true</maximize-edit>
		<instanceable>true</instanceable>
		<standalone-width>800</standalone-width>
		<standalone-height>600</standalone-height>
		<standalone-draggable>true</standalone-draggable>
		<standalone-resizable>true</standalone-resizable>
		<standalone-scrolling>auto</standalone-scrolling>
		<standalone-modal>false</standalone-modal>
		<standalone-auto-height>false</standalone-auto-height>
		<standalone-interval-time>200</standalone-interval-time>
		<header-portlet-javascript>/zkau/web/js/zk.wpd</header-portlet-javascript>
	</portlet>

	<!-- 专业树管理（多维树） -->
	<portlet>
		<portlet-name>multidimensionalTree</portlet-name>
		<maximize-edit>true</maximize-edit>
		<instanceable>true</instanceable>
		<standalone-width>800</standalone-width>
		<standalone-height>600</standalone-height>
		<standalone-draggable>true</standalone-draggable>
		<standalone-resizable>true</standalone-resizable>
		<standalone-scrolling>auto</standalone-scrolling>
		<standalone-modal>false</standalone-modal>
		<standalone-auto-height>false</standalone-auto-height>
		<standalone-interval-time>200</standalone-interval-time>
		<header-portlet-javascript>/zkau/web/js/zk.wpd</header-portlet-javascript>
	</portlet>

	<!-- 集团渠道工号较正 -->
	<portlet>
		<portlet-name>staffGrpStaff</portlet-name>
		<maximize-edit>true</maximize-edit>
		<instanceable>true</instanceable>
		<standalone-width>800</standalone-width>
		<standalone-height>600</standalone-height>
		<standalone-draggable>true</standalone-draggable>
		<standalone-resizable>true</standalone-resizable>
		<standalone-scrolling>auto</standalone-scrolling>
		<standalone-modal>false</standalone-modal>
		<standalone-auto-height>false</standalone-auto-height>
		<standalone-interval-time>200</standalone-interval-time>
		<header-portlet-javascript>/zkau/web/js/zk.wpd</header-portlet-javascript>
	</portlet>

	<!-- 角色树管理 -->
	<portlet>
		<portlet-name>rbacRoleTree</portlet-name>
		<maximize-edit>true</maximize-edit>
		<instanceable>true</instanceable>
		<standalone-width>800</standalone-width>
		<standalone-height>600</standalone-height>
		<standalone-draggable>true</standalone-draggable>
		<standalone-resizable>true</standalone-resizable>
		<standalone-scrolling>auto</standalone-scrolling>
		<standalone-modal>false</standalone-modal>
		<standalone-auto-height>false</standalone-auto-height>
		<standalone-interval-time>200</standalone-interval-time>
		<header-portlet-javascript>/zkau/web/js/zk.wpd</header-portlet-javascript>
	</portlet>

	<!-- 权限树管理 -->
	<portlet>
		<portlet-name>rbacPermissionTree</portlet-name>
		<maximize-edit>true</maximize-edit>
		<instanceable>true</instanceable>
		<standalone-width>800</standalone-width>
		<standalone-height>600</standalone-height>
		<standalone-draggable>true</standalone-draggable>
		<standalone-resizable>true</standalone-resizable>
		<standalone-scrolling>auto</standalone-scrolling>
		<standalone-modal>false</standalone-modal>
		<standalone-auto-height>false</standalone-auto-height>
		<standalone-interval-time>200</standalone-interval-time>
		<header-portlet-javascript>/zkau/web/js/zk.wpd</header-portlet-javascript>
	</portlet>

	<!-- 系统树管理 -->
	<portlet>
		<portlet-name>rbacBusinessSystemTree</portlet-name>
		<maximize-edit>true</maximize-edit>
		<instanceable>true</instanceable>
		<standalone-width>800</standalone-width>
		<standalone-height>600</standalone-height>
		<standalone-draggable>true</standalone-draggable>
		<standalone-resizable>true</standalone-resizable>
		<standalone-scrolling>auto</standalone-scrolling>
		<standalone-modal>false</standalone-modal>
		<standalone-auto-height>false</standalone-auto-height>
		<standalone-interval-time>200</standalone-interval-time>
		<header-portlet-javascript>/zkau/web/js/zk.wpd</header-portlet-javascript>
	</portlet>

	<!-- 资源树管理 -->
	<portlet>
		<portlet-name>rbacResourceTree</portlet-name>
		<maximize-edit>true</maximize-edit>
		<instanceable>true</instanceable>
		<standalone-width>800</standalone-width>
		<standalone-height>600</standalone-height>
		<standalone-draggable>true</standalone-draggable>
		<standalone-resizable>true</standalone-resizable>
		<standalone-scrolling>auto</standalone-scrolling>
		<standalone-modal>false</standalone-modal>
		<standalone-auto-height>false</standalone-auto-height>
		<standalone-interval-time>200</standalone-interval-time>
		<header-portlet-javascript>/zkau/web/js/zk.wpd</header-portlet-javascript>
	</portlet>

	<!-- 数据质量流程管理 -->
	<portlet>
		<portlet-name>bmpMgr</portlet-name>
		<maximize-edit>true</maximize-edit>
		<instanceable>true</instanceable>
		<standalone-width>800</standalone-width>
		<standalone-height>600</standalone-height>
		<standalone-draggable>true</standalone-draggable>
		<standalone-resizable>true</standalone-resizable>
		<standalone-scrolling>auto</standalone-scrolling>
		<standalone-modal>false</standalone-modal>
		<standalone-auto-height>false</standalone-auto-height>
		<standalone-interval-time>200</standalone-interval-time>
		<header-portlet-javascript>/zkau/web/js/zk.wpd</header-portlet-javascript>
	</portlet>

	<portlet>
		<portlet-name>bmpConfig</portlet-name>
		<maximize-edit>true</maximize-edit>
		<instanceable>true</instanceable>
		<standalone-width>800</standalone-width>
		<standalone-height>600</standalone-height>
		<standalone-draggable>true</standalone-draggable>
		<standalone-resizable>true</standalone-resizable>
		<standalone-scrolling>auto</standalone-scrolling>
		<standalone-modal>false</standalone-modal>
		<standalone-auto-height>false</standalone-auto-height>
		<standalone-interval-time>200</standalone-interval-time>
		<header-portlet-javascript>/zkau/web/js/zk.wpd</header-portlet-javascript>
	</portlet>
	
	<!-- 包区网点关系管理 -->
	<portlet>
		<portlet-name>channelPackareaRelation</portlet-name>
		<maximize-edit>true</maximize-edit>
		<instanceable>true</instanceable>
		<standalone-width>800</standalone-width>
		<standalone-height>600</standalone-height>
		<standalone-draggable>true</standalone-draggable>
		<standalone-resizable>true</standalone-resizable>
		<standalone-scrolling>auto</standalone-scrolling>
		<standalone-modal>false</standalone-modal>
		<standalone-auto-height>false</standalone-auto-height>
		<standalone-interval-time>200</standalone-interval-time>
		<header-portlet-javascript>/zkau/web/js/zk.wpd</header-portlet-javascript>
	</portlet>
	
	<!-- 全口径人员情况统计报表 -->
	<portlet>
		<portlet-name>fullCaliberStaffReport</portlet-name>
		<maximize-edit>true</maximize-edit>
		<instanceable>true</instanceable>
		<standalone-width>800</standalone-width>
		<standalone-height>600</standalone-height>
		<standalone-draggable>true</standalone-draggable>
		<standalone-resizable>true</standalone-resizable>
		<standalone-scrolling>auto</standalone-scrolling>
		<standalone-modal>false</standalone-modal>
		<standalone-auto-height>false</standalone-auto-height>
		<standalone-interval-time>200</standalone-interval-time>
		<header-portlet-javascript>/zkau/web/js/zk.wpd</header-portlet-javascript>
	</portlet>
	
	<!-- 批量导入 -->
	<portlet>
		<portlet-name>batchImport</portlet-name>
		<maximize-edit>true</maximize-edit>
		<instanceable>true</instanceable>
		<standalone-width>800</standalone-width>
		<standalone-height>600</standalone-height>
		<standalone-draggable>true</standalone-draggable>
		<standalone-resizable>true</standalone-resizable>
		<standalone-scrolling>auto</standalone-scrolling>
		<standalone-modal>false</standalone-modal>
		<standalone-auto-height>false</standalone-auto-height>
		<standalone-interval-time>200</standalone-interval-time>
		<header-portlet-javascript>/zkau/web/js/zk.wpd</header-portlet-javascript>
	</portlet>
	
	<portlet>
		<portlet-name>unitedDirectoryMain</portlet-name>
		<maximize-edit>true</maximize-edit>
		<instanceable>true</instanceable>
		<standalone-width>800</standalone-width>
		<standalone-height>600</standalone-height>
		<standalone-draggable>true</standalone-draggable>
		<standalone-resizable>true</standalone-resizable>
		<standalone-scrolling>auto</standalone-scrolling>
		<standalone-modal>false</standalone-modal>
		<standalone-auto-height>false</standalone-auto-height>
		<standalone-interval-time>200</standalone-interval-time>
		<header-portlet-javascript>/zkau/web/js/zk.wpd</header-portlet-javascript>
	</portlet>
	
	<!--人力组织查询列表-->
	<portlet>
		<portlet-name>hrOrganization</portlet-name>
		<maximize-edit>true</maximize-edit>
		<instanceable>true</instanceable>
		<standalone-width>800</standalone-width>
		<standalone-height>600</standalone-height>
		<standalone-draggable>true</standalone-draggable>
		<standalone-resizable>true</standalone-resizable>
		<standalone-scrolling>auto</standalone-scrolling>
		<standalone-modal>false</standalone-modal>
		<standalone-auto-height>false</standalone-auto-height>
		<standalone-interval-time>200</standalone-interval-time>
		<header-portlet-javascript>/zkau/web/js/zk.wpd</header-portlet-javascript>
	</portlet>
	
	<!-- 实名制数据统计报表  -->
	<portlet>
		<portlet-name>realnameDataReport</portlet-name>
		<maximize-edit>true</maximize-edit>
		<instanceable>true</instanceable>
		<standalone-width>800</standalone-width>
		<standalone-height>600</standalone-height>
		<standalone-draggable>true</standalone-draggable>
		<standalone-resizable>true</standalone-resizable>
		<standalone-scrolling>auto</standalone-scrolling>
		<standalone-modal>false</standalone-modal>
		<standalone-auto-height>false</standalone-auto-height>
		<standalone-interval-time>200</standalone-interval-time>
		<header-portlet-javascript>/zkau/web/js/zk.wpd</header-portlet-javascript>
	</portlet>
	
	<!-- 包区网点关系审批 -->
	<portlet>
		<portlet-name>channelPackareaApprove</portlet-name>
		<maximize-edit>true</maximize-edit>
		<instanceable>true</instanceable>
		<standalone-width>800</standalone-width>
		<standalone-height>600</standalone-height>
		<standalone-draggable>true</standalone-draggable>
		<standalone-resizable>true</standalone-resizable>
		<standalone-scrolling>auto</standalone-scrolling>
		<standalone-modal>false</standalone-modal>
		<standalone-auto-height>false</standalone-auto-height>
		<standalone-interval-time>200</standalone-interval-time>
		<header-portlet-javascript>/zkau/web/js/zk.wpd</header-portlet-javascript>
	</portlet>
	
	<!--PI财务组织查询列表-->
	<portlet>
		<portlet-name>piFinanceOrg</portlet-name>
		<maximize-edit>true</maximize-edit>
		<instanceable>true</instanceable>
		<standalone-width>800</standalone-width>
		<standalone-height>600</standalone-height>
		<standalone-draggable>true</standalone-draggable>
		<standalone-resizable>true</standalone-resizable>
		<standalone-scrolling>auto</standalone-scrolling>
		<standalone-modal>false</standalone-modal>
		<standalone-auto-height>false</standalone-auto-height>
		<standalone-interval-time>200</standalone-interval-time>
		<header-portlet-javascript>/zkau/web/js/zk.wpd</header-portlet-javascript>
	</portlet>
	
	<!--UAC员工综合管理-->
	<portlet>
		<portlet-name>uacStaff</portlet-name>
		<maximize-edit>true</maximize-edit>
		<instanceable>true</instanceable>
		<standalone-width>800</standalone-width>
		<standalone-height>600</standalone-height>
		<standalone-draggable>true</standalone-draggable>
		<standalone-resizable>true</standalone-resizable>
		<standalone-scrolling>auto</standalone-scrolling>
		<standalone-modal>false</standalone-modal>
		<standalone-auto-height>false</standalone-auto-height>
		<standalone-interval-time>200</standalone-interval-time>
		<header-portlet-javascript>/zkau/web/js/zk.wpd</header-portlet-javascript>
	</portlet>
	
	<!--内蒙古电信全口径用工管理-->
	<!-- 人员信息管理-基本信息维护 -->
	<portlet>
		<portlet-name>baseInfo</portlet-name>
		<maximize-edit>true</maximize-edit>
		<instanceable>true</instanceable>
		<standalone-width>800</standalone-width>
		<standalone-height>600</standalone-height>
		<standalone-draggable>true</standalone-draggable>
		<standalone-resizable>true</standalone-resizable>
		<standalone-scrolling>auto</standalone-scrolling>
		<standalone-modal>false</standalone-modal>
		<standalone-auto-height>false</standalone-auto-height>
		<standalone-interval-time>200</standalone-interval-time>
		<header-portlet-javascript>/zkau/web/js/zk.wpd</header-portlet-javascript>
	</portlet>
	<!-- 人员信息管理-账号管理 -->
	<portlet>
		<portlet-name>accountManage</portlet-name>
		<maximize-edit>true</maximize-edit>
		<instanceable>true</instanceable>
		<standalone-width>800</standalone-width>
		<standalone-height>600</standalone-height>
		<standalone-draggable>true</standalone-draggable>
		<standalone-resizable>true</standalone-resizable>
		<standalone-scrolling>auto</standalone-scrolling>
		<standalone-modal>false</standalone-modal>
		<standalone-auto-height>false</standalone-auto-height>
		<standalone-interval-time>200</standalone-interval-time>
		<header-portlet-javascript>/zkau/web/js/zk.wpd</header-portlet-javascript>
	</portlet>
	<!-- 人员信息管理-家庭信息管理 -->
	<portlet>
		<portlet-name>familyInformation</portlet-name>
		<maximize-edit>true</maximize-edit>
		<instanceable>true</instanceable>
		<standalone-width>800</standalone-width>
		<standalone-height>600</standalone-height>
		<standalone-draggable>true</standalone-draggable>
		<standalone-resizable>true</standalone-resizable>
		<standalone-scrolling>auto</standalone-scrolling>
		<standalone-modal>false</standalone-modal>
		<standalone-auto-height>false</standalone-auto-height>
		<standalone-interval-time>200</standalone-interval-time>
		<header-portlet-javascript>/zkau/web/js/zk.wpd</header-portlet-javascript>
	</portlet>
	<!-- 人员信息管理-政治面貌管理 -->
	<portlet>
		<portlet-name>politicalStatus</portlet-name>
		<maximize-edit>true</maximize-edit>
		<instanceable>true</instanceable>
		<standalone-width>800</standalone-width>
		<standalone-height>600</standalone-height>
		<standalone-draggable>true</standalone-draggable>
		<standalone-resizable>true</standalone-resizable>
		<standalone-scrolling>auto</standalone-scrolling>
		<standalone-modal>false</standalone-modal>
		<standalone-auto-height>false</standalone-auto-height>
		<standalone-interval-time>200</standalone-interval-time>
		<header-portlet-javascript>/zkau/web/js/zk.wpd</header-portlet-javascript>
	</portlet>
	<!-- 人员信息管理-军队退役管理 -->
	<portlet>
		<portlet-name>militaryDischarge</portlet-name>
		<maximize-edit>true</maximize-edit>
		<instanceable>true</instanceable>
		<standalone-width>800</standalone-width>
		<standalone-height>600</standalone-height>
		<standalone-draggable>true</standalone-draggable>
		<standalone-resizable>true</standalone-resizable>
		<standalone-scrolling>auto</standalone-scrolling>
		<standalone-modal>false</standalone-modal>
		<standalone-auto-height>false</standalone-auto-height>
		<standalone-interval-time>200</standalone-interval-time>
		<header-portlet-javascript>/zkau/web/js/zk.wpd</header-portlet-javascript>
	</portlet>
	<!-- 岗位信息管理-岗位信息管理 -->
	<portlet>
		<portlet-name>baseInformation</portlet-name>
		<maximize-edit>true</maximize-edit>
		<instanceable>true</instanceable>
		<standalone-width>800</standalone-width>
		<standalone-height>600</standalone-height>
		<standalone-draggable>true</standalone-draggable>
		<standalone-resizable>true</standalone-resizable>
		<standalone-scrolling>auto</standalone-scrolling>
		<standalone-modal>false</standalone-modal>
		<standalone-auto-height>false</standalone-auto-height>
		<standalone-interval-time>200</standalone-interval-time>
		<header-portlet-javascript>/zkau/web/js/zk.wpd</header-portlet-javascript>
	</portlet>
	<!-- 岗位信息管理-岗位序列管理 -->
	<portlet>
		<portlet-name>positionSequence</portlet-name>
		<maximize-edit>true</maximize-edit>
		<instanceable>true</instanceable>
		<standalone-width>800</standalone-width>
		<standalone-height>600</standalone-height>
		<standalone-draggable>true</standalone-draggable>
		<standalone-resizable>true</standalone-resizable>
		<standalone-scrolling>auto</standalone-scrolling>
		<standalone-modal>false</standalone-modal>
		<standalone-auto-height>false</standalone-auto-height>
		<standalone-interval-time>200</standalone-interval-time>
		<header-portlet-javascript>/zkau/web/js/zk.wpd</header-portlet-javascript>
	</portlet>
	<!-- 组织机构管理-基本信息管理 -->
	<portlet>
		<portlet-name>orgBaseInfo</portlet-name>
		<maximize-edit>true</maximize-edit>
		<instanceable>true</instanceable>
		<standalone-width>800</standalone-width>
		<standalone-height>600</standalone-height>
		<standalone-draggable>true</standalone-draggable>
		<standalone-resizable>true</standalone-resizable>
		<standalone-scrolling>auto</standalone-scrolling>
		<standalone-modal>false</standalone-modal>
		<standalone-auto-height>false</standalone-auto-height>
		<standalone-interval-time>200</standalone-interval-time>
		<header-portlet-javascript>/zkau/web/js/zk.wpd</header-portlet-javascript>
	</portlet>
	<!-- 组织机构管理-组织关系管理 -->
	<portlet>
		<portlet-name>orgRelations</portlet-name>
		<maximize-edit>true</maximize-edit>
		<instanceable>true</instanceable>
		<standalone-width>800</standalone-width>
		<standalone-height>600</standalone-height>
		<standalone-draggable>true</standalone-draggable>
		<standalone-resizable>true</standalone-resizable>
		<standalone-scrolling>auto</standalone-scrolling>
		<standalone-modal>false</standalone-modal>
		<standalone-auto-height>false</standalone-auto-height>
		<standalone-interval-time>200</standalone-interval-time>
		<header-portlet-javascript>/zkau/web/js/zk.wpd</header-portlet-javascript>
	</portlet>
	<!-- 组织机构管理-负责人信息管理 -->
	<portlet>
		<portlet-name>fuzerenInformation</portlet-name>
		<maximize-edit>true</maximize-edit>
		<instanceable>true</instanceable>
		<standalone-width>800</standalone-width>
		<standalone-height>600</standalone-height>
		<standalone-draggable>true</standalone-draggable>
		<standalone-resizable>true</standalone-resizable>
		<standalone-scrolling>auto</standalone-scrolling>
		<standalone-modal>false</standalone-modal>
		<standalone-auto-height>false</standalone-auto-height>
		<standalone-interval-time>200</standalone-interval-time>
		<header-portlet-javascript>/zkau/web/js/zk.wpd</header-portlet-javascript>
	</portlet>
	<!-- 组织机构管理-成本中心数据 -->
	<portlet>
		<portlet-name>costCenterData</portlet-name>
		<maximize-edit>true</maximize-edit>
		<instanceable>true</instanceable>
		<standalone-width>800</standalone-width>
		<standalone-height>600</standalone-height>
		<standalone-draggable>true</standalone-draggable>
		<standalone-resizable>true</standalone-resizable>
		<standalone-scrolling>auto</standalone-scrolling>
		<standalone-modal>false</standalone-modal>
		<standalone-auto-height>false</standalone-auto-height>
		<standalone-interval-time>200</standalone-interval-time>
		<header-portlet-javascript>/zkau/web/js/zk.wpd</header-portlet-javascript>
	</portlet>
	<!-- 组织机构管理-成本中心关系 -->
	<portlet>
		<portlet-name>costCenterRel</portlet-name>
		<maximize-edit>true</maximize-edit>
		<instanceable>true</instanceable>
		<standalone-width>800</standalone-width>
		<standalone-height>600</standalone-height>
		<standalone-draggable>true</standalone-draggable>
		<standalone-resizable>true</standalone-resizable>
		<standalone-scrolling>auto</standalone-scrolling>
		<standalone-modal>false</standalone-modal>
		<standalone-auto-height>false</standalone-auto-height>
		<standalone-interval-time>200</standalone-interval-time>
		<header-portlet-javascript>/zkau/web/js/zk.wpd</header-portlet-javascript>
	</portlet>
	<!-- 入离职管理-任职信息管理 -->
	<portlet>
		<portlet-name>officalInformation</portlet-name>
		<maximize-edit>true</maximize-edit>
		<instanceable>true</instanceable>
		<standalone-width>800</standalone-width>
		<standalone-height>600</standalone-height>
		<standalone-draggable>true</standalone-draggable>
		<standalone-resizable>true</standalone-resizable>
		<standalone-scrolling>auto</standalone-scrolling>
		<standalone-modal>false</standalone-modal>
		<standalone-auto-height>false</standalone-auto-height>
		<standalone-interval-time>200</standalone-interval-time>
		<header-portlet-javascript>/zkau/web/js/zk.wpd</header-portlet-javascript>
	</portlet>
	<!-- 入离职管理-离退管理 -->
	<portlet>
		<portlet-name>officalLeave</portlet-name>
		<maximize-edit>true</maximize-edit>
		<instanceable>true</instanceable>
		<standalone-width>800</standalone-width>
		<standalone-height>600</standalone-height>
		<standalone-draggable>true</standalone-draggable>
		<standalone-resizable>true</standalone-resizable>
		<standalone-scrolling>auto</standalone-scrolling>
		<standalone-modal>false</standalone-modal>
		<standalone-auto-height>false</standalone-auto-height>
		<standalone-interval-time>200</standalone-interval-time>
		<header-portlet-javascript>/zkau/web/js/zk.wpd</header-portlet-javascript>
	</portlet>
	<!-- 入离职管理-组织关系管理 -->
	<portlet>
		<portlet-name>officalOrganization</portlet-name>
		<maximize-edit>true</maximize-edit>
		<instanceable>true</instanceable>
		<standalone-width>800</standalone-width>
		<standalone-height>600</standalone-height>
		<standalone-draggable>true</standalone-draggable>
		<standalone-resizable>true</standalone-resizable>
		<standalone-scrolling>auto</standalone-scrolling>
		<standalone-modal>false</standalone-modal>
		<standalone-auto-height>false</standalone-auto-height>
		<standalone-interval-time>200</standalone-interval-time>
		<header-portlet-javascript>/zkau/web/js/zk.wpd</header-portlet-javascript>
	</portlet>	
	<!-- 入离职管理-合同管理 -->
	<portlet>
		<portlet-name>officalContract</portlet-name>
		<maximize-edit>true</maximize-edit>
		<instanceable>true</instanceable>
		<standalone-width>800</standalone-width>
		<standalone-height>600</standalone-height>
		<standalone-draggable>true</standalone-draggable>
		<standalone-resizable>true</standalone-resizable>
		<standalone-scrolling>auto</standalone-scrolling>
		<standalone-modal>false</standalone-modal>
		<standalone-auto-height>false</standalone-auto-height>
		<standalone-interval-time>200</standalone-interval-time>
		<header-portlet-javascript>/zkau/web/js/zk.wpd</header-portlet-javascript>
	</portlet>	
	<!-- 职业技能管理-职业资格管理 -->
	<portlet>
		<portlet-name>proQualification</portlet-name>
		<maximize-edit>true</maximize-edit>
		<instanceable>true</instanceable>
		<standalone-width>800</standalone-width>
		<standalone-height>600</standalone-height>
		<standalone-draggable>true</standalone-draggable>
		<standalone-resizable>true</standalone-resizable>
		<standalone-scrolling>auto</standalone-scrolling>
		<standalone-modal>false</standalone-modal>
		<standalone-auto-height>false</standalone-auto-height>
		<standalone-interval-time>200</standalone-interval-time>
		<header-portlet-javascript>/zkau/web/js/zk.wpd</header-portlet-javascript>
	</portlet>
	<portlet>
		<portlet-name>specialWorker</portlet-name>
		<maximize-edit>true</maximize-edit>
		<instanceable>true</instanceable>
		<standalone-width>800</standalone-width>
		<standalone-height>600</standalone-height>
		<standalone-draggable>true</standalone-draggable>
		<standalone-resizable>true</standalone-resizable>
		<standalone-scrolling>auto</standalone-scrolling>
		<standalone-modal>false</standalone-modal>
		<standalone-auto-height>false</standalone-auto-height>
		<standalone-interval-time>200</standalone-interval-time>
		<header-portlet-javascript>/zkau/web/js/zk.wpd</header-portlet-javascript>
	</portlet>	
	<portlet>
		<portlet-name>majorWorker</portlet-name>
		<maximize-edit>true</maximize-edit>
		<instanceable>true</instanceable>
		<standalone-width>800</standalone-width>
		<standalone-height>600</standalone-height>
		<standalone-draggable>true</standalone-draggable>
		<standalone-resizable>true</standalone-resizable>
		<standalone-scrolling>auto</standalone-scrolling>
		<standalone-modal>false</standalone-modal>
		<standalone-auto-height>false</standalone-auto-height>
		<standalone-interval-time>200</standalone-interval-time>
		<header-portlet-javascript>/zkau/web/js/zk.wpd</header-portlet-javascript>
	</portlet>	
	<portlet>
		<portlet-name>backboneWorker</portlet-name>
		<maximize-edit>true</maximize-edit>
		<instanceable>true</instanceable>
		<standalone-width>800</standalone-width>
		<standalone-height>600</standalone-height>
		<standalone-draggable>true</standalone-draggable>
		<standalone-resizable>true</standalone-resizable>
		<standalone-scrolling>auto</standalone-scrolling>
		<standalone-modal>false</standalone-modal>
		<standalone-auto-height>false</standalone-auto-height>
		<standalone-interval-time>200</standalone-interval-time>
		<header-portlet-javascript>/zkau/web/js/zk.wpd</header-portlet-javascript>
	</portlet>	
	<portlet>
		<portlet-name>authorizedPatent</portlet-name>
		<maximize-edit>true</maximize-edit>
		<instanceable>true</instanceable>
		<standalone-width>800</standalone-width>
		<standalone-height>600</standalone-height>
		<standalone-draggable>true</standalone-draggable>
		<standalone-resizable>true</standalone-resizable>
		<standalone-scrolling>auto</standalone-scrolling>
		<standalone-modal>false</standalone-modal>
		<standalone-auto-height>false</standalone-auto-height>
		<standalone-interval-time>200</standalone-interval-time>
		<header-portlet-javascript>/zkau/web/js/zk.wpd</header-portlet-javascript>
	</portlet>	
	<portlet>
		<portlet-name>professionalSkill</portlet-name>
		<maximize-edit>true</maximize-edit>
		<instanceable>true</instanceable>
		<standalone-width>800</standalone-width>
		<standalone-height>600</standalone-height>
		<standalone-draggable>true</standalone-draggable>
		<standalone-resizable>true</standalone-resizable>
		<standalone-scrolling>auto</standalone-scrolling>
		<standalone-modal>false</standalone-modal>
		<standalone-auto-height>false</standalone-auto-height>
		<standalone-interval-time>200</standalone-interval-time>
		<header-portlet-javascript>/zkau/web/js/zk.wpd</header-portlet-javascript>
	</portlet>												
	
	<!-- 教育培训管理-教育经历管理 -->
	<portlet>
		<portlet-name>eduExperience</portlet-name>
		<maximize-edit>true</maximize-edit>
		<instanceable>true</instanceable>
		<standalone-width>800</standalone-width>
		<standalone-height>600</standalone-height>
		<standalone-draggable>true</standalone-draggable>
		<standalone-resizable>true</standalone-resizable>
		<standalone-scrolling>auto</standalone-scrolling>
		<standalone-modal>false</standalone-modal>
		<standalone-auto-height>false</standalone-auto-height>
		<standalone-interval-time>200</standalone-interval-time>
		<header-portlet-javascript>/zkau/web/js/zk.wpd</header-portlet-javascript>
	</portlet>	
	<portlet>
		<portlet-name>languageSkill</portlet-name>
		<maximize-edit>true</maximize-edit>
		<instanceable>true</instanceable>
		<standalone-width>800</standalone-width>
		<standalone-height>600</standalone-height>
		<standalone-draggable>true</standalone-draggable>
		<standalone-resizable>true</standalone-resizable>
		<standalone-scrolling>auto</standalone-scrolling>
		<standalone-modal>false</standalone-modal>
		<standalone-auto-height>false</standalone-auto-height>
		<standalone-interval-time>200</standalone-interval-time>
		<header-portlet-javascript>/zkau/web/js/zk.wpd</header-portlet-javascript>
	</portlet>
	<portlet>
		<portlet-name>trainingMag</portlet-name>
		<maximize-edit>true</maximize-edit>
		<instanceable>true</instanceable>
		<standalone-width>800</standalone-width>
		<standalone-height>600</standalone-height>
		<standalone-draggable>true</standalone-draggable>
		<standalone-resizable>true</standalone-resizable>
		<standalone-scrolling>auto</standalone-scrolling>
		<standalone-modal>false</standalone-modal>
		<standalone-auto-height>false</standalone-auto-height>
		<standalone-interval-time>200</standalone-interval-time>
		<header-portlet-javascript>/zkau/web/js/zk.wpd</header-portlet-javascript>
	</portlet>					
	<!-- 奖惩管理-奖励管理 -->
	<portlet>
		<portlet-name>rewardMag</portlet-name>
		<maximize-edit>true</maximize-edit>
		<instanceable>true</instanceable>
		<standalone-width>800</standalone-width>
		<standalone-height>600</standalone-height>
		<standalone-draggable>true</standalone-draggable>
		<standalone-resizable>true</standalone-resizable>
		<standalone-scrolling>auto</standalone-scrolling>
		<standalone-modal>false</standalone-modal>
		<standalone-auto-height>false</standalone-auto-height>
		<standalone-interval-time>200</standalone-interval-time>
		<header-portlet-javascript>/zkau/web/js/zk.wpd</header-portlet-javascript>
	</portlet>		
	<!-- 奖惩管理-处罚管理 -->
	<portlet>
		<portlet-name>punishmentMag</portlet-name>
		<maximize-edit>true</maximize-edit>
		<instanceable>true</instanceable>
		<standalone-width>800</standalone-width>
		<standalone-height>600</standalone-height>
		<standalone-draggable>true</standalone-draggable>
		<standalone-resizable>true</standalone-resizable>
		<standalone-scrolling>auto</standalone-scrolling>
		<standalone-modal>false</standalone-modal>
		<standalone-auto-height>false</standalone-auto-height>
		<standalone-interval-time>200</standalone-interval-time>
		<header-portlet-javascript>/zkau/web/js/zk.wpd</header-portlet-javascript>
	</portlet>		
	<!-- 福利查询-福利种类查询 -->
	<portlet>
		<portlet-name>welfareType</portlet-name>
		<maximize-edit>true</maximize-edit>
		<instanceable>true</instanceable>
		<standalone-width>800</standalone-width>
		<standalone-height>600</standalone-height>
		<standalone-draggable>true</standalone-draggable>
		<standalone-resizable>true</standalone-resizable>
		<standalone-scrolling>auto</standalone-scrolling>
		<standalone-modal>false</standalone-modal>
		<standalone-auto-height>false</standalone-auto-height>
		<standalone-interval-time>200</standalone-interval-time>
		<header-portlet-javascript>/zkau/web/js/zk.wpd</header-portlet-javascript>
	</portlet>		
	<!-- 福利查询-福利发放查询 -->
	<portlet>
		<portlet-name>welfareUsing</portlet-name>
		<maximize-edit>true</maximize-edit>
		<instanceable>true</instanceable>
		<standalone-width>800</standalone-width>
		<standalone-height>600</standalone-height>
		<standalone-draggable>true</standalone-draggable>
		<standalone-resizable>true</standalone-resizable>
		<standalone-scrolling>auto</standalone-scrolling>
		<standalone-modal>false</standalone-modal>
		<standalone-auto-height>false</standalone-auto-height>
		<standalone-interval-time>200</standalone-interval-time>
		<header-portlet-javascript>/zkau/web/js/zk.wpd</header-portlet-javascript>
	</portlet>	
		
	<!--个人自助-个人信息查询 -->
	<portlet>
		<portlet-name>selfDataquery</portlet-name>
		<maximize-edit>true</maximize-edit>
		<instanceable>true</instanceable>
		<standalone-width>800</standalone-width>
		<standalone-height>600</standalone-height>
		<standalone-draggable>true</standalone-draggable>
		<standalone-resizable>true</standalone-resizable>
		<standalone-scrolling>auto</standalone-scrolling>
		<standalone-modal>false</standalone-modal>
		<standalone-auto-height>false</standalone-auto-height>
		<standalone-interval-time>200</standalone-interval-time>
		<header-portlet-javascript>/zkau/web/js/zk.wpd</header-portlet-javascript>
	</portlet>		


	
	
	
	
	
	
	
	
	
	
	
	
	
	
	
	
	
	
	<!-- 结束 -->
	<role-mapper>
		<role-name>administrator</role-name>
		<role-link>Administrator</role-link>
	</role-mapper>
	<role-mapper>
		<role-name>guest</role-name>
		<role-link>Guest</role-link>
	</role-mapper>
	<role-mapper>
		<role-name>power-user</role-name>
		<role-link>Power User</role-link>
	</role-mapper>
	<role-mapper>
		<role-name>user</role-name>
		<role-link>User</role-link>
	</role-mapper>
</raptornuke-portlet-app>